{
  "3131": {
    "close": 194.39,
    "close_date": "2020-04-30"
  },
  "3680": {
    "close": 145.35,
    "close_date": "2020-04-30"
  },
  "6683": {
    "close": 180.41,
    "close_date": "2020-04-30"
  },
  "6187": {
    "close": 35.13,
    "close_date": "2020-04-30"
  },
  "6223": {
    "close": 55.72,
    "close_date": "2020-04-30"
  },
  "3013": {
    "close": 11.94,
    "close_date": "2020-04-30"
  },
  "3017": {
    "close": 35.44,
    "close_date": "2020-04-30"
  },
  "3583": {
    "close": 40.83,
    "close_date": "2020-04-30"
  },
  "3324": {
    "close": 148.3,
    "close_date": "2020-04-30"
  },
  "2486": {
    "close": 7.14,
    "close_date": "2020-04-30"
  },
  "3450": {
    "close": 64.16,
    "close_date": "2020-04-30"
  },
  "8027": {
    "close": 31.74,
    "close_date": "2020-04-30"
  }
}